LICENSE
README.md
pyh264/__init__.py
pyh264/encoder.py
pyh264/__os__/__init__.py
pyh264/__os__/converter_darwin
pyh264/__os__/converter_linux
py_h264-0.2.2.dist-info/METADATA
py_h264-0.2.2.dist-info/WHEEL
py_h264-0.2.2.dist-info/licenses/LICENSE
py_h264-0.2.2.dist-info/RECORD
