Metadata-Version: 2.4
Name: py-h264
Version: 0.2.2
Summary: A Python library for encoding videos to H.264 and converting images to videos.
Project-URL: Documentation, https://github.com/orphanbyte/py-h264#readme
Project-URL: Source, https://github.com/orphanbyte/py-h264
Project-URL: Issues, https://github.com/orphanbyte/py-h264/issues
Author-email: Orphan Byte <orphanbyte@proton.me>
License: MIT License
License-File: LICENSE
Classifier: Development Status :: 4 - Beta
Classifier: Intended Audience :: Developers
Classifier: License :: OSI Approved :: MIT License
Classifier: Operating System :: POSIX :: Linux
Classifier: Programming Language :: Python :: 3
Classifier: Programming Language :: Python :: 3.8
Classifier: Programming Language :: Python :: 3.9
Classifier: Programming Language :: Python :: 3.10
Classifier: Programming Language :: Python :: 3.11
Classifier: Programming Language :: Python :: 3.12
Classifier: Programming Language :: Python :: 3.13
Classifier: Topic :: Multimedia :: Graphics
Classifier: Topic :: Multimedia :: Video
Classifier: Topic :: Multimedia :: Video :: Conversion
Classifier: Topic :: Software Development :: Libraries :: Python Modules
Requires-Python: >=3.8
